memory_graph/__init__.py
memory_graph/call_stack.py
memory_graph/config.py
memory_graph/config_default.py
memory_graph/config_helpers.py
memory_graph/extension_numpy.py
memory_graph/extension_pandas.py
memory_graph/extension_torch.py
memory_graph/html_table.py
memory_graph/list_view.py
memory_graph/memory_to_nodes.py
memory_graph/node_base.py
memory_graph/node_key_value.py
memory_graph/node_leaf.py
memory_graph/node_linear.py
memory_graph/node_table.py
memory_graph/sequence.py
memory_graph/slicer.py
memory_graph/slices.py
memory_graph/slices_iterator.py
memory_graph/slices_table_iterator.py
memory_graph/test.py
memory_graph/test_max_graph_depth.py
memory_graph/test_memory_graph.py
memory_graph/test_memory_to_nodes.py
memory_graph/test_sequence.py
memory_graph/test_slicer.py
memory_graph/test_slices.py
memory_graph/test_slices_iterator.py
memory_graph/utils.py
memory_graph-0.3.64.dist-info/licenses/LICENSE.txt
memory_graph-0.3.64.dist-info/METADATA
memory_graph-0.3.64.dist-info/WHEEL
memory_graph-0.3.64.dist-info/top_level.txt
memory_graph-0.3.64.dist-info/RECORD
