Metadata-Version: 2.4
Name: memory_graph
Version: 0.3.64
Summary: Teaching tool and debugging aid in context of references, mutable data types, and shallow and deep copy.
Author-email: Bas Terwijn <bterwijn@gmail.com>
License-Expression: BSD-2-Clause
Project-URL: Homepage, https://github.com/bterwijn/memory_graph
Project-URL: Repository, https://github.com/bterwijn/memory_graph.git
Classifier: Development Status :: 4 - Beta
Classifier: Intended Audience :: Education
Classifier: Intended Audience :: Developers
Classifier: Programming Language :: Python :: 3
Classifier: Topic :: Education
Classifier: Topic :: Software Development :: Debuggers
Requires-Python: >=3.7
License-File: LICENSE.txt
Requires-Dist: graphviz
Dynamic: license-file
